setup.cfg
setup.py
namespace/__init__.py
namespace/namespace.py
pcattori_namespace.egg-info/PKG-INFO
pcattori_namespace.egg-info/SOURCES.txt
pcattori_namespace.egg-info/dependency_links.txt
pcattori_namespace.egg-info/pbr.json
pcattori_namespace.egg-info/top_level.txt