Metadata-Version: 1.0
Name: pcattori-namespace
Version: 1.0.1
Summary: Python dictionaries with attributes instead of keys
Home-page: https://github.com/pcattori/namespace
Author: Pedro Cattori
Author-email: pcattori@gmail.com
License: MIT
Platform: UNKNOWN
